iniabu/__init__.py
iniabu/elements.py
iniabu/isotopes.py
iniabu/main.py
iniabu/utilities.py
iniabu/data/__init__.py
iniabu/data/asplund09.py
iniabu/data/lodders09.py
iniabu/data/nist15.py
iniabu/data/nist15_isomasses_all.py
iniabu-1.2.1.dist-info/METADATA
iniabu-1.2.1.dist-info/WHEEL
iniabu-1.2.1.dist-info/licenses/LICENSE
iniabu-1.2.1.dist-info/RECORD
