Metadata-Version: 2.4
Name: iniabu
Version: 1.2.1
Summary: Read solar system abundances and automatically calculate various metrics, e.g., delta-values, dex, etc.
Project-URL: Source, https://github.com/galactic-forensics/iniabu
Project-URL: Documentation, https://iniabu.readthedocs.io
Author-email: Reto Trappitsch <reto@galactic-forensics.space>
License: GPLv2
License-File: LICENSE
Requires-Python: >=3.9
Requires-Dist: numpy>=2.0
Provides-Extra: doc
Requires-Dist: sphinx-rtd-theme>=2.0.0; extra == 'doc'
Requires-Dist: sphinx<8.0; extra == 'doc'
